ecomapper/__init__.py
ecomapper/main.py
ecomapper/core/__init__.py
ecomapper/core/fragment.py
ecomapper/core/journal.py
ecomapper/core/merge.py
ecomapper/core/safe_context_manager.py
ecomapper/launchers/__init__.py
ecomapper/launchers/eval_launcher.py
ecomapper/launchers/mmseg_test.py
ecomapper/launchers/predict_launcher.py
ecomapper/launchers/train_launcher.py
ecomapper/mmseg_interface/__init__.py
ecomapper/mmseg_interface/mask2former_config_wrapper.py
ecomapper/mmseg_interface/mmseg_config_wrapper.py
ecomapper/mmseg_interface/registry.py
ecomapper/task/__init__.py
ecomapper/task/dataset_task.py
ecomapper/task/pipeline_task.py
ecomapper/task/predict_task.py
ecomapper/task/task.py
ecomapper/task/train_task.py
ecomapper/task/unlabeled_dataset_task.py
ecomapper/utils/__init__.py
ecomapper/utils/date_util.py
ecomapper/utils/file_util.py
ecomapper/utils/geo_image_util.py
ecomapper/utils/joblib_util.py
ecomapper/utils/json_util.py
ecomapper/utils/numpy_util.py
ecomapper/utils/path_util.py
ecomapper/utils/print_util.py
ecomapper/utils/prompt_util.py
ecomapper/utils/random_util.py
ecomapper/utils/signal_util.py
ecomapper/utils/torch_util.py
ecomapper/utils/tqdm_util.py
ecomapper-1.0.0.dist-info/METADATA
ecomapper-1.0.0.dist-info/WHEEL
ecomapper-1.0.0.dist-info/licenses/LICENSE
ecomapper-1.0.0.dist-info/RECORD
