Metadata-Version: 2.4
Name: ecomapper
Version: 1.0.0
Summary: Pipeline for segmentation of arbitrary features in remote sensing imagery using deep learning
Project-URL: Homepage, https://github.com/hcording/ecomapper
Project-URL: Bug Tracker, https://github.com/hcording/ecomapper/issues
Author-email: Henry Cording <henry.cording@pm.me>
License-File: LICENSE
Classifier: License :: OSI Approved :: GNU General Public License v3 (GPLv3)
Classifier: Operating System :: OS Independent
Classifier: Programming Language :: Python :: 3
Requires-Python: ~=3.10
